FPLTransfers/FPLTransfers.py
FPLTransfers/__init__.py
FPLTransfers-0.1.dist-info/LICENSE
FPLTransfers-0.1.dist-info/METADATA
FPLTransfers-0.1.dist-info/WHEEL
FPLTransfers-0.1.dist-info/top_level.txt
FPLTransfers-0.1.dist-info/RECORD
